proteyn/Protein.py
proteyn/__init__.py
proteyn-0.0.1.dist-info/METADATA
proteyn-0.0.1.dist-info/WHEEL
proteyn-0.0.1.dist-info/licenses/LICENSE
proteyn-0.0.1.dist-info/RECORD
