Metadata-Version: 2.1
Name: proteyn
Version: 0.0.1
Summary: Computational Protein Design Library for Python Developers
Project-URL: Homepage, https://github.com/Tdsone/proteyn
Project-URL: Bug Tracker, https://github.com/Tdsone/proteyn/issues
Author-email: Timon Schneider <mail@timonschneider.de>
License-File: LICENSE
Classifier: Operating System :: OS Independent
Classifier: Programming Language :: Python :: 3
Requires-Python: >=3.7
